_foo.cpython-38-x86_64-linux-gnu.so
tfmiss/__init__.py
tfmiss/keras/testing_utils.py
tfmiss/keras/__init__.py
tfmiss/keras/callbacks/lrfind.py
tfmiss/keras/callbacks/__init__.py
tfmiss/keras/optimizers/__init__.py
tfmiss/keras/optimizers/schedules/whca.py
tfmiss/keras/optimizers/schedules/__init__.py
tfmiss/keras/layers/dcnv2.py
tfmiss/keras/layers/todense.py
tfmiss/keras/layers/reduction.py
tfmiss/keras/layers/dropout.py
tfmiss/keras/layers/tcn.py
tfmiss/keras/layers/attention.py
tfmiss/keras/layers/embedding.py
tfmiss/keras/layers/wrappers.py
tfmiss/keras/layers/wordvec.py
tfmiss/keras/layers/__init__.py
tfmiss/keras/layers/preprocessing.py
tfmiss/keras/layers/softmax.py
tfmiss/keras/layers/scale.py
tfmiss/keras/layers/qrnn.py
tfmiss/keras/losses/__init__.py
tfmiss/keras/losses/f1.py
tfmiss/keras/losses/bitemp.py
tfmiss/keras/metrics/__init__.py
tfmiss/keras/metrics/f1.py
tfmiss/training/bucket.py
tfmiss/training/__init__.py
tfmiss/training/adapt.py
tfmiss/preprocessing/sampling.py
tfmiss/preprocessing/__init__.py
tfmiss/preprocessing/preprocessing.py
tfmiss/text/wordpiecelib.py
tfmiss/text/unicode_transform.py
tfmiss/text/wordpiece.py
tfmiss/text/__init__.py
tfmiss/text/unicode_expand.py
tfmiss/nn/dcnv2.py
tfmiss/nn/embedding.py
tfmiss/nn/__init__.py
tfmiss/nn/qrnn.py
tfmiss/ops/_tfmiss_ops.so
tfmiss/ops/__init__.py
tfmiss-0.17.1.dist-info/WHEEL
tfmiss-0.17.1.dist-info/RECORD
tfmiss-0.17.1.dist-info/METADATA
tfmiss-0.17.1.dist-info/top_level.txt
tfmiss-0.17.1.dist-info/LICENSE
