Metadata-Version: 2.1
Name: tfmiss
Version: 0.17.1
Summary: Missing layers, ops & etc. for TensorFlow
Home-page: https://github.com/shkarupa-alex/tfmiss
Author: Shkarupa Alex
Author-email: shkarupa.alex@gmail.com
License: MIT
Keywords: tensorflow layers ops
Platform: UNKNOWN
Classifier: Development Status :: 5 - Production/Stable
Classifier: Intended Audience :: Developers
Classifier: Intended Audience :: Education
Classifier: Intended Audience :: Science/Research
Classifier: License :: OSI Approved :: MIT License
Classifier: Programming Language :: Python :: 3.6
Classifier: Programming Language :: Python :: 3.7
Classifier: Programming Language :: Python :: 3.8
Classifier: Topic :: Scientific/Engineering
Classifier: Topic :: Scientific/Engineering :: Artificial Intelligence
Classifier: Topic :: Software Development
Classifier: Topic :: Software Development :: Libraries
Classifier: Topic :: Software Development :: Libraries :: Python Modules
Requires-Dist: absl-py (>=1.0.0)
Requires-Dist: keras (>=2.9.0)
Requires-Dist: matplotlib (>=3.5.1)
Requires-Dist: nlpvocab (>=1.2.0)
Requires-Dist: scipy (>=1.7.3)
Requires-Dist: tabulate (>=0.8.9)
Requires-Dist: tensorflow (==2.9.1)
